tests/__init__.py
tests/test_001_imports.py
tests/test_002_run_eag.py
tests/test_003_run_gaf.py
tests/test_004_plots.py
tests/test_005_benchmarks.py
waterbalans/__init__.py
waterbalans/buckets.py
waterbalans/create.py
waterbalans/eag.py
waterbalans/gaf.py
waterbalans/plots.py
waterbalans/run_utils.py
waterbalans/timeseries.py
waterbalans/utils.py
waterbalans/version.py
waterbalans/water.py
waterbalans/wsdl_settings.py
waterbalans-0.1.2.dist-info/LICENSE
waterbalans-0.1.2.dist-info/METADATA
waterbalans-0.1.2.dist-info/WHEEL
waterbalans-0.1.2.dist-info/top_level.txt
waterbalans-0.1.2.dist-info/RECORD
