Metadata-Version: 2.1
Name: waterbalans
Version: 0.1.2
Summary: Python Package voor het maken van Waternet Waterbalansen
Home-page: https://github.com/ArtesiaWater/waterbalans
Author: Davíd Brakenhoff
Author-email: d.brakenhoff@artesia-water.nl
License: MIT
Project-URL: Source, https://github.com/ArtesiaWater/waterbalans
Project-URL: Documentation, https://waterbalans.readthedocs.io/en/latest/
Project-URL: Tracker, https://github.com/ArtesiaWater/waterbalans/issues
Project-URL: Help, https://github.com/ArtesiaWater/waterbalans/discussions
Platform: Windows
Platform: Mac OS-X
Classifier: Development Status :: 4 - Beta
Classifier: Intended Audience :: Science/Research
Classifier: Intended Audience :: Other Audience
Classifier: License :: OSI Approved :: MIT License
Classifier: Programming Language :: Python :: 3
Classifier: Topic :: Scientific/Engineering :: Hydrology
License-File: LICENSE
Requires-Dist: numpy (>=1.19.2)
Requires-Dist: matplotlib (>=3.4.1)
Requires-Dist: pandas (>=1.3.0)
Requires-Dist: scipy (>=0.19)
